{
    "themes": {
        "theme": [
            {
                "id": "animals",
                "name": "Animal Welfare"
            },
            {
                "id": "children",
                "name": "Child Protection"
            },
            {
                "id": "climate",
                "name": "Climate Action"
            },
            {
                "id": "democ",
                "name": "Peace and Reconciliation"
            },
            {
                "id": "disaster",
                "name": "Disaster Response"
            },
            {
                "id": "ecdev",
                "name": "Economic Growth"
            },
            {
                "id": "edu",
                "name": "Education"
            },
            {
                "id": "env",
                "name": "Ecosystem Restoration"
            },
            {
                "id": "gender",
                "name": "Gender Equality"
            },
            {
                "id": "health",
                "name": "Physical Health"
            },
            {
                "id": "human",
                "name": "Ending Human Trafficking"
            },
            {
                "id": "rights",
                "name": "Justice and Human Rights"
            },
            {
                "id": "sport",
                "name": "Sport"
            },
            {
                "id": "tech",
                "name": "Digital Literacy"
            },
            {
                "id": "hunger",
                "name": "Food Security"
            },
            {
                "id": "art",
                "name": "Arts and Culture"
            },
            {
                "id": "lgbtq",
                "name": "LGBTQIA+ Equality"
            },
            {
                "id": "covid-19",
                "name": "COVID-19"
            },
            {
                "id": "water",
                "name": "Clean Water"
            },
            {
                "id": "disability",
                "name": "Disability Rights"
            },
            {
                "id": "endabuse",
                "name": "Ending Abuse"
            },
            {
                "id": "mentalhealth",
                "name": "Mental Health"
            },
            {
                "id": "justice",
                "name": "Racial Justice"
            },
            {
                "id": "refugee",
                "name": "Refugee Rights"
            },
            {
                "id": "reproductive",
                "name": "Reproductive Health"
            },
            {
                "id": "housing",
                "name": "Safe Housing"
            },
            {
                "id": "agriculture",
                "name": "Sustainable Agriculture"
            },
            {
                "id": "wildlife",
                "name": "Wildlife Conservation"
            }
        ]
    }
}